[{"dtype": "compas.robots/Configuration", "value": {"joint_values": [0.22543950503505386, 4.1863559323211, -2.128157823532675, -0.48740178185057037, 1.570796326774756, 1.7962358319763632], "joint_types": [0, 0, 0, 0, 0, 0], "joint_names": ["shoulder_pan_joint", "shoulder_lift_joint", "elbow_joint", "wrist_1_joint", "wrist_2_joint", "wrist_3_joint"]}}, {"dtype": "compas.robots/Configuration", "value": {"joint_values": [0.007901970936273085, 4.290723853038192, -2.3657503122829597, -0.3541772138571336, 1.5707963267597995, 1.5786982978775823], "joint_types": [0, 0, 0, 0, 0, 0], "joint_names": ["shoulder_pan_joint", "shoulder_lift_joint", "elbow_joint", "wrist_1_joint", "wrist_2_joint", "wrist_3_joint"]}}, {"dtype": "compas.robots/Configuration", "value": {"joint_values": [-0.2970941910357429, 4.338561100168961, -2.4807640312912613, -0.2870007420300579, 1.5707963267263736, 1.2737021359055665], "joint_types": [0, 0, 0, 0, 0, 0], "joint_names": ["shoulder_pan_joint", "shoulder_lift_joint", "elbow_joint", "wrist_1_joint", "wrist_2_joint", "wrist_3_joint"]}}, {"dtype": "compas.robots/Configuration", "value": {"joint_values": [-0.6727032873282716, 4.328464259426434, -2.455960259902468, -0.3017076727256331, 1.5707963266673475, 0.8980930396130378], "joint_types": [0, 0, 0, 0, 0, 0], "joint_names": ["shoulder_pan_joint", "shoulder_lift_joint", "elbow_joint", "wrist_1_joint", "wrist_2_joint", "wrist_3_joint"]}}, {"dtype": "compas.robots/Configuration", "value": {"joint_values": [-1.0513929203281926, 4.269047884398387, -2.31526837199375, -0.382983185635511, 1.5707963265909162, 0.5194034066131167], "joint_types": [0, 0, 0, 0, 0, 0], "joint_names": ["shoulder_pan_joint", "shoulder_lift_joint", "elbow_joint", "wrist_1_joint", "wrist_2_joint", "wrist_3_joint"]}}, {"dtype": "compas.robots/Configuration", "value": {"joint_values": [-1.39290658673543, 4.17901907748399, -2.111854544969079, -0.4963682057475407, 1.5707963265120748, 0.1778897402058791], "joint_types": [0, 0, 0, 0, 0, 0], "joint_names": ["shoulder_pan_joint", "shoulder_lift_joint", "elbow_joint", "wrist_1_joint", "wrist_2_joint", "wrist_3_joint"]}}, {"dtype": "compas.robots/Configuration", "value": {"joint_values": [-1.6913940944985015, 4.089756158800758, -1.9159369487359978, -0.603022883275098, 1.5707963264423344, -0.12059776755719262], "joint_types": [0, 0, 0, 0, 0, 0], "joint_names": ["shoulder_pan_joint", "shoulder_lift_joint", "elbow_joint", "wrist_1_joint", "wrist_2_joint", "wrist_3_joint"]}}, {"dtype": "compas.robots/Configuration", "value": {"joint_values": [-1.9609183958983738, 4.027180212130509, -1.7804902256945716, -0.6758936596066428, 1.5707963263855653, -0.39012206895706486], "joint_types": [0, 0, 0, 0, 0, 0], "joint_names": ["shoulder_pan_joint", "shoulder_lift_joint", "elbow_joint", "wrist_1_joint", "wrist_2_joint", "wrist_3_joint"]}}, {"dtype": "compas.robots/Configuration", "value": {"joint_values": [-2.2151951568715504, 3.981330059673213, -1.6818990107892384, -0.7286347220026412, 1.5707963263422882, -0.6443988299302414], "joint_types": [0, 0, 0, 0, 0, 0], "joint_names": ["shoulder_pan_joint", "shoulder_lift_joint", "elbow_joint", "wrist_1_joint", "wrist_2_joint", "wrist_3_joint"]}}, {"dtype": "compas.robots/Configuration", "value": {"joint_values": [-2.4614541696957026, 3.9288345995017373, -1.5695136342468192, -0.7885246383126049, 1.5707963263131273, -0.8906578427543934], "joint_types": [0, 0, 0, 0, 0, 0], "joint_names": ["shoulder_pan_joint", "shoulder_lift_joint", "elbow_joint", "wrist_1_joint", "wrist_2_joint", "wrist_3_joint"]}}, {"dtype": "compas.robots/Configuration", "value": {"joint_values": [-2.693397599060551, 3.8507440761369414, -1.4030353104989945, -0.8769124386315136, 1.5707963262995026, -1.1226012721192418], "joint_types": [0, 0, 0, 0, 0, 0], "joint_names": ["shoulder_pan_joint", "shoulder_lift_joint", "elbow_joint", "wrist_1_joint", "wrist_2_joint", "wrist_3_joint"]}}]